birdhousebuilder.recipe.ncwms-0.2.0-py2.7-nspkg.pth
birdhousebuilder/recipe/ncwms/__init__.py
birdhousebuilder/recipe/ncwms/config.properties
birdhousebuilder/recipe/ncwms/config.properties~
birdhousebuilder/recipe/ncwms/config.xml
birdhousebuilder/recipe/ncwms/config.xml~
birdhousebuilder/recipe/ncwms/tests/__init__.py
birdhousebuilder/recipe/ncwms/tests/test_docs.py
birdhousebuilder.recipe.ncwms-0.2.0.dist-info/DESCRIPTION.rst
birdhousebuilder.recipe.ncwms-0.2.0.dist-info/METADATA
birdhousebuilder.recipe.ncwms-0.2.0.dist-info/RECORD
birdhousebuilder.recipe.ncwms-0.2.0.dist-info/WHEEL
birdhousebuilder.recipe.ncwms-0.2.0.dist-info/entry_points.txt
birdhousebuilder.recipe.ncwms-0.2.0.dist-info/metadata.json
birdhousebuilder.recipe.ncwms-0.2.0.dist-info/namespace_packages.txt
birdhousebuilder.recipe.ncwms-0.2.0.dist-info/pbr.json
birdhousebuilder.recipe.ncwms-0.2.0.dist-info/top_level.txt
