Metadata-Version: 2.0
Name: birdhousebuilder.recipe.ncwms
Version: 0.2.0
Summary: A Buildout recipe to install and configure ncWMS2 server with Anaconda.
Home-page: https://github.com/bird-house/birdhousebuilder.recipe.ncwms
Author: Birdhouse
Author-email: UNKNOWN
License: BSD
Keywords: buildout recipe wms ncwms tomcat birdhouse conda anaconda
Platform: UNKNOWN
Classifier: Framework :: Buildout
Classifier: Intended Audience :: Developers
Classifier: Topic :: Software Development :: Build Tools
Classifier: Topic :: Software Development :: Libraries :: Python Modules
Classifier: License :: OSI Approved :: BSD License
Requires-Dist: Mako
Requires-Dist: birdhousebuilder.recipe.conda
Requires-Dist: birdhousebuilder.recipe.tomcat
Requires-Dist: setuptools
Requires-Dist: zc.buildout
Provides-Extra: tests
Requires-Dist: manuel; extra == 'tests'
Requires-Dist: zc.buildout; extra == 'tests'
Requires-Dist: zope.testing; extra == 'tests'
